pinancial/__init__.py
pinancial/example.py
pinancial-0.0.1.dist-info/METADATA
pinancial-0.0.1.dist-info/WHEEL
pinancial-0.0.1.dist-info/licenses/LICENSE
pinancial-0.0.1.dist-info/RECORD
