Metadata-Version: 2.1
Name: pinancial
Version: 0.0.1
Summary: API wrapper for financial services.
Project-URL: Homepage, https://github.com/nnayda/pinancial
Project-URL: Bug Tracker, https://github.com/nnayda/pinancial/issues
Author-email: Nathan Nayda <ntnayda@gmail.com>
License-File: LICENSE
Classifier: License :: OSI Approved :: MIT License
Classifier: Operating System :: OS Independent
Classifier: Programming Language :: Python :: 3
Requires-Python: >=3.7
